{
  "1": {
    "video_id": "video12_19740",
    "frame_number": 19744,
    "objects": [
      {
        "query": "open grasper",
        "pixel_x": 333,
        "pixel_y": 142,
        "pixel_coords_numpy": [
          142,
          333
        ]
      }
    ],
    "actions": []
  },
  "3": {
    "video_id": "video12_19740",
    "frame_number": 19752,
    "objects": [],
    "actions": [
      {
        "query": "grasper going to grasp the gallbladder",
        "pixel_x": 362,
        "pixel_y": 189,
        "pixel_coords_numpy": [
          189,
          362
        ]
      }
    ]
  },
  "7": {
    "video_id": "video12_19740",
    "frame_number": 19768,
    "objects": [],
    "actions": [
      {
        "query": "gallbladder squeezed by grasper",
        "pixel_x": 379,
        "pixel_y": 149,
        "pixel_coords_numpy": [
          149,
          379
        ]
      }
    ]
  },
  "17": {
    "video_id": "video12_19740",
    "frame_number": 19808,
    "objects": [],
    "actions": [
      {
        "query": "grasper letting go of gallbladder",
        "pixel_x": 509,
        "pixel_y": 156,
        "pixel_coords_numpy": [
          156,
          509
        ]
      }
    ]
  }
}